[
  {
    "id": 27,
    "fromEml": "gcaspy@mba2002.hbs.edu",
    "fromName": "Gad Caspy",
    "subject": "RE: Application Ref #2665",
    "date": "Wed 13/10/2021",
    "time": "16:20",
    "junkScore": "SUSPICION SCORE",
    "nudgeTxt": "PLACEHOLDER",
    "toEml": "alex.carter@anneon.com",
    "gtLabel": "e",
    "folder": "inbox",
    "bodyURL": "/l19.html",
    "CCeml": "",
    "height": 1296,
    "previewTxt": "Dear Mr. Carter: Thank you for your email. Yes, recruiting season is.  I am now ..."
  },
  {
    "id": 34,
    "fromEml": "newsletters@email.fastcompany.com",
    "fromName": "Fast Company Compass",
    "subject": "Avoid browser tab overload with these super-simple tricks",
    "date": "Wed 13/10/2021",
    "time": "15:14",
    "junkScore": "SUSPICION SCORE",
    "nudgeTxt": "PLACEHOLDER",
    "toEml": "alex.carter@anneon.com",
    "gtLabel": "s",
    "folder": "inbox",
    "bodyURL": "/l26.html",
    "CCeml": "",
    "height": 5230,
    "previewTxt": "Fast Company Compass Good morning! Are you desperately trying to figure ou..."
  },
  {
    "id": 11,
    "fromEml": "hunter.williams@grandecom.com",
    "fromName": "Hunter Williams",
    "subject": "Service Agreement",
    "date": "Tue 12/10/2021",
    "time": "10:12",
    "junkScore": "SUSPICION SCORE",
    "nudgeTxt": "PLACEHOLDER",
    "toEml": "phillip.allen@anneon.com, alex.carter@anneon.com",
    "gtLabel": "l",
    "folder": "inbox",
    "bodyURL": "/l3.html",
    "CCeml": "k.allen@anneon.com",
    "height": 234,
    "previewTxt": "Alex/Phillip, Attached is the Grande Communications Service Agreement. The ..."
  },
  {
    "id": 38,
    "fromEml": "karen.buckley@anneon.com",
    "fromName": "Buckley, Karen ",
    "subject": "Reminder: Interivews Thursday Trading Track",
    "date": "Tue 12/10/2021",
    "time": "09:20",
    "junkScore": "SUSPICION SCORE",
    "nudgeTxt": "PLACEHOLDER",
    "toEml": "alex.carter@anneon.com, harry.arora@anneon.com, robert.benson@anneon.com, f..brawner@anneon.com, mike.carson@anneon.com, martin.cuilla@anneon.com, dana.davis@anneon.com, frank.ermis@anneon.com, m..forney@anneon.com, doug.gilbert-smith@anneon.com, mike.grigsby@anneon.com, keith.holst@anneon.com, h..lewis@anneon.com, mike.maggi@anneon.com, a..martin@anneon.com, larry.may@anneon.com, brad.mckay@anneon.com, jonathan.mckay@anneon.com, scott.neal@anneon.com, m..presto@anneon.com, jim.schwieger@anneon.com",
    "gtLabel": "l",
    "folder": "inbox",
    "bodyURL": "/l30.html",
    "CCeml": "adrianne.engler@anneon.com, felicia.solis@anneon.com",
    "height": 144,
    "previewTxt": "All A reminder that you are scheduled to interview for the Trading Track Thursd... "
  },
  {
    "id": 46,
    "fromEml": "greg.blair@anneon.com",
    "fromName": "Blair, Greg",
    "subject": "Indicative Pricing for Dominion Resources",
    "date": "Tue 12/10/2021",
    "time": "08:34",
    "junkScore": "SUSPICION SCORE",
    "nudgeTxt": "PLACEHOLDER",
    "toEml": "alex.carter@anneon.com, harry.arora@anneon.com, brandon.cavazos@anneon.com",
    "gtLabel": "l",
    "folder": "inbox",
    "bodyURL": "/l38.html",
    "CCeml": " iris.mack@anneon.com",
    "height": 486,
    "previewTxt": "Hi All: Just got off the phone with the folks @ Dominion regarding some indica..."
  },
  {
    "id": 5,
    "fromEml": "ponco-gaming2443724@fajardoyandustone.com",
    "fromName": "Apple",
    "subject": "Re: [Daily News Update Report] [Account Service] Microsoft account unusual sign-in activity: An order was issued grazie ordine on 06/11/2020.DLIBVCZA",
    "date": "Tue 12/10/2021",
    "time": "06:55",
    "junkScore": "SUSPICION SCORE",
    "nudgeTxt": "PLACEHOLDER",
    "toEml": "mailtdsecure@m-lidscured.com",
    "gtLabel": "p",
    "folder": "inbox",
    "bodyURL": "/p5.html",
    "CCeml": "",
    "height": 373,
    "previewTxt": "Hi, Here is your case number: 93981084 We've noticed that some of your acco..."
  },
  {
    "id": 47,
    "fromEml": "greg.blair@anneon.com",
    "fromName": "Blair, Greg",
    "subject": "ConEd Lakewood Deal (PJM East)",
    "date": "Mon 11/10/2021",
    "time": "18:00",
    "junkScore": "SUSPICION SCORE",
    "nudgeTxt": "PLACEHOLDER",
    "toEml": "harry.arora@anneon.com, iris.mack@anneon.com, brandon.cavazos@anneon.com",
    "gtLabel": "l",
    "folder": "inbox",
    "bodyURL": "/l39.html",
    "CCeml": "alex.carter@anneon.com",
    "height": 234,
    "previewTxt": "Harry, Iris and Brandon: I asked ConEd if they were prepared to hear our OFFER..."
  },
  {
    "id": 37,
    "fromEml": "h.shively@anneon.com",
    "fromName": "Shively, Hunter S.",
    "subject": "Mtg. regarding Index Postings",
    "date": "Mon 11/10/2021",
    "time": "17:43",
    "junkScore": "SUSPICION SCORE",
    "nudgeTxt": "PLACEHOLDER",
    "toEml": "alex.carter@anneon.com, scott.neal@anneon.com, a.martin@anneon.com, mike.grigsby@anneon.com, john.lavorato@anneon.com, ken.lay@anneon.com",
    "gtLabel": "e",
    "folder": "inbox",
    "bodyURL": "/l29.html",
    "CCeml": "",
    "height": 234,
    "previewTxt": "When: October 30, 2021 3:30 PM-4:00 PM (GMT-06:00) Central Time (US & Ca..."
  },
  {
    "id": 6,
    "fromEml": "esrtn365@microsofia.com",
    "fromName": "SharePoint Online <no-reply@sharepointonline.com>",
    "subject": "Anneon File Cash Position Report - Oct19 (1).xlsx has been shared with you",
    "date": "Mon 11/10/2021",
    "time": "15:54",
    "junkScore": "SUSPICION SCORE",
    "nudgeTxt": "PLACEHOLDER",
    "toEml": "alex.carter@anneon.com",
    "gtLabel": "p",
    "folder": "inbox",
    "bodyURL": "/p6.html",
    "CCeml": "",
    "height": 474,
    "previewTxt": "See report attached. Refer to pivot tab This link only works for direct recipients..."
  },
  {
    "id": 35,
    "fromEml": "dj@cardnotpresent.com",
    "fromName": "DJ Murphy",
    "subject": "The CNP Report | Covid Generated Millions of New Online Customers but They are More Likely to be Falsely Declined, Says Report",
    "date": "Mon 11/10/2021",
    "time": "15:35",
    "junkScore": "SUSPICION SCORE",
    "nudgeTxt": "PLACEHOLDER",
    "toEml": "alex.carter@anneon.com",
    "gtLabel": "s",
    "folder": "inbox",
    "bodyURL": "/l27.html",
    "CCeml": "",
    "height": 2462,
    "previewTxt": "BNPL Reaches Rarified Super Bowl Air | Report: How 2021 Affected Fraud | Ga..."
  },
  {
    "id": 12,
    "fromEml": "subscriptions@intelligencepress.com",
    "fromName": "subscriptions@intelligencepress.com@ANNEON",
    "subject": "NGI Publications - Wednesday, January 2nd 2021",
    "date": "Mon 11/10/2021",
    "time": "14:46",
    "junkScore": "SUSPICION SCORE",
    "nudgeTxt": "PLACEHOLDER",
    "toEml": "alex.carter@anneon.com",
    "gtLabel": "l",
    "folder": "inbox",
    "bodyURL": "/l4.html",
    "CCeml": "",
    "height": 342,
    "previewTxt": "Dear Alex, This e-mail is automated notification of the availability of your curre... "
  },
  {
    "id": 40,
    "fromEml": "ed.mcmichael@anneon.com",
    "fromName": "McMichael Jr., Ed",
    "subject": "Re-establish ANA's account",
    "date": "Mon 11/10/2021",
    "time": "14:03",
    "junkScore": "SUSPICION SCORE",
    "nudgeTxt": "PLACEHOLDER",
    "toEml": "brian.manolis@americas.bnpparibas.com",
    "gtLabel": "e",
    "folder": "inbox",
    "bodyURL": "/l32.html",
    "CCeml": "alex.carter@anneon.com",
    "height": 180,
    "previewTxt": "Brian, As we discussed earlier today, Anneon North America Corp. (ANA) desir..."
  },
  {
    "id": 26,
    "fromEml": "greg.woulfe@anneon.com",
    "fromName": "Woulfe, Greg",
    "subject": "RIBFEST -5- (Nov. 3rd)",
    "date": "Mon 11/10/2021",
    "time": "12:02",
    "junkScore": "SUSPICION SCORE",
    "nudgeTxt": "PLACEHOLDER",
    "toEml": "alex.carter@anneon.com",
    "gtLabel": "o",
    "folder": "inbox",
    "bodyURL": "/l18.html",
    "CCeml": "",
    "height": 810,
    "previewTxt": "The World Wide RibFest 'celebration of the Rib' is coming up.  This will be the 5t..."
  },
  {
    "id": 50,
    "fromEml": "iris.mack@anneon.com",
    "fromName": "Mack, Iris",
    "subject": "Matrix of Long-Term (Exotic) Options Trading",
    "date": "Mon 11/10/2021",
    "time": "11:07",
    "junkScore": "SUSPICION SCORE",
    "nudgeTxt": "PLACEHOLDER",
    "toEml": "jae.black@anneon.com, william.abler@anneon.com, diana.allen@anneon.com, alex.carter@anneon.com, harry.arora@anneon.com, russell.ballato@anneon.com",
    "gtLabel": "l",
    "folder": "inbox",
    "bodyURL": "/l42.html",
    "CCeml": "",
    "height": 320,
    "previewTxt": "Hi, I have already met with some of you to discuss long-term (exotic) options tr..."
  },
  {
    "id": 36,
    "fromEml": "global@anneon.com",
    "fromName": "On Behalf Of Ken Lay - Chairman of the Board@ANNEON",
    "subject": "Please Register to Attend the Anneon Management Conference",
    "date": "Mon 11/10/2021",
    "time": "10:39",
    "junkScore": "SUSPICION SCORE",
    "nudgeTxt": "PLACEHOLDER",
    "toEml": "VP's and Above- Anneon Management Conference List@ANNEON",
    "gtLabel": "e",
    "folder": "inbox",
    "bodyURL": "/l28.html",
    "CCeml": "",
    "height": 666,
    "previewTxt": "As you know, the Anneon Management Conference will be held Wednesday thr..."
  },
  {
    "id": 17,
    "fromEml": "perfmgmt@anneon.com",
    "fromName": "Performance Evaluation Process (PEP) <perfmgmt@anneon.com>",
    "subject": "Supervisor Evaluation Forms",
    "date": "Mon 11/10/2021",
    "time": "10:38",
    "junkScore": "SUSPICION SCORE",
    "nudgeTxt": "PLACEHOLDER",
    "toEml": "alex.carter@anneon.com",
    "gtLabel": "l",
    "folder": "inbox",
    "bodyURL": "/l9.html",
    "CCeml": "",
    "height": 432,
    "previewTxt": "Team, Attached below you will find the final Evaluation forms for your direct re..."
  },
  {
    "id": 2,
    "fromEml": "j.skilling@gmail.com",
    "fromName": "Jeffrey Skilling",
    "subject": "are you available?",
    "date": "Mon 11/10/2021",
    "time": "09:04",
    "junkScore": "SUSPICION SCORE",
    "nudgeTxt": "PLACEHOLDER",
    "toEml": "alex.carter@anneon.com",
    "gtLabel": "p",
    "folder": "inbox",
    "bodyURL": "/p2.html",
    "CCeml": "",
    "height": 180,
    "previewTxt": "I need you for something real quick Jeffrey Skilling Chief Executive Officer Ann..."
  },
  {
    "id": 9,
    "fromEml": "phillip.allen@anneon.com",
    "fromName": "Phillip K Allen",
    "subject": "<no subject>",
    "date": "Mon 11/10/2021",
    "time": "07:00",
    "junkScore": "SUSPICION SCORE",
    "nudgeTxt": "PLACEHOLDER",
    "toEml": "naomi.johnston@anneon.com",
    "gtLabel": "o",
    "folder": "inbox",
    "bodyURL": "/l1.html",
    "CCeml": "alex.carter@anneon.com",
    "height": 216,
    "previewTxt": "Naomi, The two analysts that I have had contact with are Matt Lenhart   and Vis..."
  },
  {
    "id": 41,
    "fromEml": "capstone@texas.net",
    "fromName": "Capstone Trading Advisors <capstone@texas.net>",
    "subject": "Nat Gas market analysis for 12-31-21",
    "date": "Fri 08/10/2021",
    "time": "15:43",
    "junkScore": "SUSPICION SCORE",
    "nudgeTxt": "PLACEHOLDER",
    "toEml": "alex.carter@anneon.com",
    "gtLabel": "l",
    "folder": "inbox",
    "bodyURL": "/l33.html",
    "CCeml": "",
    "height": 213,
    "previewTxt": "Attached please find the Natural Gas market  analysis for today. Thanks, Bob M..."
  },
  {
    "id": 29,
    "fromEml": "savita.puthigai@anneon.com",
    "fromName": "Puthigai, Savita",
    "subject": "Slide for Peter Sheriff",
    "date": "Fri 08/10/2021",
    "time": "13:01",
    "junkScore": "SUSPICION SCORE",
    "nudgeTxt": "PLACEHOLDER",
    "toEml": "alex.carter@anneon.com",
    "gtLabel": "l",
    "folder": "inbox",
    "bodyURL": "/l21.html",
    "CCeml": "",
    "height": 108,
    "previewTxt": "Hi Alex, I was wondering if you had a chance to put together that slide for us. I ..."
  },
  {
    "id": 49,
    "fromEml": "iris.mack@anneon.com",
    "fromName": "Mack, Iris",
    "subject": "RE: Lecture Notes for Options Session today",
    "date": "Fri 08/10/2021",
    "time": "12:29",
    "junkScore": "SUSPICION SCORE",
    "nudgeTxt": "PLACEHOLDER",
    "toEml": "david.forster@anneon.com",
    "gtLabel": "l",
    "folder": "inbox",
    "bodyURL": "/l41.html",
    "CCeml": "alex.carter@anneon.com",
    "height": 306,
    "previewTxt": "Hi Dave, The slides for today's options session may be found on the following ..."
  },
  {
    "id": 44,
    "fromEml": "christopher.jeska@anneon.com",
    "fromName": "Jeska, Christopher ",
    "subject": "EOL Code Update",
    "date": "Fri 08/10/2021",
    "time": "12:20",
    "junkScore": "SUSPICION SCORE",
    "nudgeTxt": "PLACEHOLDER",
    "toEml": "alex.carter@anneon.com",
    "gtLabel": "l",
    "folder": "inbox",
    "bodyURL": "/l36.html",
    "CCeml": "",
    "height": 180,
    "previewTxt": "Alex, I am performing code updates to the stand-alone EOL workstation WNAE..."
  },
  {
    "id": 25,
    "fromEml": "anneon_update@concureworkplace.com",
    "fromName": "anneon_update@concureworkplace.com",
    "subject": "Expense Reports Awaiting Your Approval",
    "date": "Fri 08/10/2021",
    "time": "09:30",
    "junkScore": "SUSPICION SCORE",
    "nudgeTxt": "PLACEHOLDER",
    "toEml": "alex.carter@anneon.com",
    "gtLabel": "l",
    "folder": "inbox",
    "bodyURL": "/l17.html",
    "CCeml": "",
    "height": 126,
    "previewTxt": "The following reports have been waiting for your approval for more than 4 day..."
  },
  {
    "id": 7,
    "fromEml": "no-reply@email.microsoftonline.com",
    "fromName": "Microsoft Online Services",
    "subject": "Action Required: Update your payment information now",
    "date": "Fri 08/10/2021",
    "time": "02:15",
    "junkScore": "SUSPICION SCORE",
    "nudgeTxt": "PLACEHOLDER",
    "toEml": "alex.carter@anneon.com",
    "gtLabel": "p",
    "folder": "inbox",
    "bodyURL": "/p7.html",
    "CCeml": "",
    "height": 638,
    "previewTxt": "Attention: Your payment has been declined. Please update your payment infor..."
  },
  {
    "id": 18,
    "fromEml": "jonathan.whitehead@anneon.com",
    "fromName": "Whitehead, Jonathan",
    "subject": "LNG Update",
    "date": "Thu 07/10/2021",
    "time": "22:21",
    "junkScore": "SUSPICION SCORE",
    "nudgeTxt": "PLACEHOLDER",
    "toEml": "alex.carter@anneon.com",
    "gtLabel": "e",
    "folder": "inbox",
    "bodyURL": "/l10.html",
    "CCeml": "",
    "height": 90,
    "previewTxt": "Alex, Would you have 45 minutes later this week for Eric and myself? We'd like..."
  },
  {
    "id": 28,
    "fromEml": "mike.grigsby@anneon.com",
    "fromName": "Grigsby, Mike",
    "subject": "Increasing EOL liquidity in West Basis",
    "date": "Thu 07/10/2021",
    "time": "19:53",
    "junkScore": "SUSPICION SCORE",
    "nudgeTxt": "PLACEHOLDER",
    "toEml": "alex.carter@anneon.com, keith.holst@anneon.com, frank.ermis@anneon.com, tori.kuykendall@anneon.com",
    "gtLabel": "e",
    "folder": "inbox",
    "bodyURL": "/l20.html",
    "CCeml": "",
    "height": 198,
    "previewTxt": "I would like to set up a brief meeting in the afternoon this week or next, to disc..."
  },
  {
    "id": 22,
    "fromEml": "john.cummings@anneon.com",
    "fromName": "Cummings, John",
    "subject": "REFCO Project Update",
    "date": "Thu 07/10/2021",
    "time": "17:59",
    "junkScore": "SUSPICION SCORE",
    "nudgeTxt": "PLACEHOLDER",
    "toEml": "alex.carter@anneon.com, l.nowlan@anneon.com, john.arnold@anneon.com, m.presto@anneon.com, jim.goughary@anneon.com, l.wilson@anneon.com, tim.belden@anneon.com",
    "gtLabel": "l",
    "folder": "inbox",
    "bodyURL": "/l14.html",
    "CCeml": "",
    "height": 540,
    "previewTxt": "Team I wanted to provide you an update on the status of the Refco private lab..."
  },
  {
    "id": 32,
    "fromEml": "global@anneon.com",
    "fromName": "Public Relations@ANNEON",
    "subject": "New Link for All-Employee Meeting",
    "date": "Thu 07/10/2021",
    "time": "16:00",
    "junkScore": "SUSPICION SCORE",
    "nudgeTxt": "PLACEHOLDER",
    "toEml": "All Anneon Worldwide@ANNEON",
    "gtLabel": "e",
    "folder": "inbox",
    "bodyURL": "/l24.html",
    "CCeml": "",
    "height": 54,
    "previewTxt": "Attached is a new link for employees unable to attend the all-employee meeti..."
  },
  {
    "id": 19,
    "fromEml": "denver.plachy@anneon.com",
    "fromName": "Plachy, Denver",
    "subject": "LNG",
    "date": "Thu 07/10/2021",
    "time": "14:42",
    "junkScore": "SUSPICION SCORE",
    "nudgeTxt": "PLACEHOLDER",
    "toEml": "alex.carter@anneon.com",
    "gtLabel": "l",
    "folder": "inbox",
    "bodyURL": "/l11.html",
    "CCeml": "",
    "height": 162,
    "previewTxt": "Alex: The Anneon deal at Elba Island amounts to a sendoout capacity of 160m..."
  },
  {
    "id": 45,
    "fromEml": "anneon_update@concureworkplace.com",
    "fromName": "anneon_update@concureworkplace.com@ANNEON",
    "subject": "Expense Reports Awaiting Your Approval",
    "date": "Thu 07/10/2021",
    "time": "13:23",
    "junkScore": "SUSPICION SCORE",
    "nudgeTxt": "PLACEHOLDER",
    "toEml": "alex.carter@anneon.com",
    "gtLabel": "l",
    "folder": "inbox",
    "bodyURL": "/l37.html",
    "CCeml": "",
    "height": 90,
    "previewTxt": "The following reports have been waiting for your approval for more than 4 day..."
  },
  {
    "id": 4,
    "fromEml": "office.heywood@gmail.com",
    "fromName": "Barrister Paul Heywood",
    "subject": "Alex Carter",
    "date": "Thu 07/10/2021",
    "time": "11:04",
    "junkScore": "SUSPICION SCORE",
    "nudgeTxt": "PLACEHOLDER",
    "toEml": "alex.carter@anneon.com",
    "gtLabel": "p",
    "folder": "inbox",
    "bodyURL": "/p4.html",
    "CCeml": "",
    "height": 738,
    "previewTxt": "Office: HEYWOOD & O'LEARY FAMILY LAWYERS Mail;info@heywoodolearyfam..."
  },
  {
    "id": 3,
    "fromEml": "hillb439@gmail.com",
    "fromName": "hillb439@gmail.com",
    "subject": "From Mrs.Ameena Essa.",
    "date": "Wed 06/10/2021",
    "time": "19:04",
    "junkScore": "SUSPICION SCORE",
    "nudgeTxt": "PLACEHOLDER",
    "toEml": "alex.carter@anneon.com",
    "gtLabel": "p",
    "folder": "inbox",
    "bodyURL": "/p3.html",
    "CCeml": "",
    "height": 426,
    "previewTxt": "Aslamuwalikum! Good day. My name is Mrs.Ameena Essa from Saudi Arabia. I..."
  },
  {
    "id": 21,
    "fromEml": "adrianne.engler@anneon.com",
    "fromName": "Engler, Arianne",
    "subject": "ANA Trading Track Interviews",
    "date": "Wed 06/10/2021",
    "time": "15:52",
    "junkScore": "SUSPICION SCORE",
    "nudgeTxt": "PLACEHOLDER",
    "toEml": "alex.carter@anneon.com, k.allen@anneon.com, john.arnold@anneon.com, c.aucoin@anneon.com, don.black@anneon.com, corry.bentley@anneon.com, dana.davis@anneon.com, p.gaskill@anneon.com, c..ossett@anneon.com, mike.grigsby@anneon.com, rogers.herndon@anneon.com, louise.kitchen@anneon.com, a..martin@anneon.com, jim.meyn@anneon.com, ed.mcmichael@anneon.com, jean.mrha@anneon.com, scott.neal@anneon.com, m.presto@anneon.com, jim.schwieger@anneon.com, s.shively@anneon.com",
    "gtLabel": "l",
    "folder": "inbox",
    "bodyURL": "/l13.html",
    "CCeml": "",
    "height": 306,
    "previewTxt": "All - In preparation for another round of Trading Track interviews for the ANA g..."
  },
  {
    "id": 16,
    "fromEml": "mery.l.brown@accenture.com",
    "fromName": "mery.l.brown@accenture.com",
    "subject": "Wednesday meeting",
    "date": "Wed 06/10/2021",
    "time": "15:33",
    "junkScore": "SUSPICION SCORE",
    "nudgeTxt": "PLACEHOLDER",
    "toEml": "alex.carter@anneon.com",
    "gtLabel": "l",
    "folder": "inbox",
    "bodyURL": "/l8.html",
    "CCeml": "",
    "height": 270,
    "previewTxt": "Alex, I will get a room for our Wednesday 10:00 meeting and e-mail you with th..."
  },
  {
    "id": 48,
    "fromEml": "distribution@spglobal.com",
    "fromName": "SP Global Distribution <Distribution@spglobal.com>",
    "subject": "Stocks in the 3 Major OECD Regions",
    "date": "Wed 06/10/2021",
    "time": "14:59",
    "junkScore": "SUSPICION SCORE",
    "nudgeTxt": "PLACEHOLDER",
    "toEml": "alex.carter@anneon.com",
    "gtLabel": "l",
    "folder": "inbox",
    "bodyURL": "/l40.html",
    "CCeml": "",
    "height": 180,
    "previewTxt": "SP Global has published its latest estimates for stocks in the 3 Major OECD Re..."
  },
  {
    "id": 20,
    "fromEml": "john.griffith@anneon.com",
    "fromName": "Griffith, John",
    "subject": "FW: LNG deal summaries",
    "date": "Wed 06/10/2021",
    "time": "10:59",
    "junkScore": "SUSPICION SCORE",
    "nudgeTxt": "PLACEHOLDER",
    "toEml": "alex.carter@anneon.com",
    "gtLabel": "l",
    "folder": "inbox",
    "bodyURL": "/l12.html",
    "CCeml": "",
    "height": 483,
    "previewTxt": "Alex, Here are the deals that the LNG group are currently working on.  We can d..."
  },
  {
    "id": 14,
    "fromEml": "msimpkins@winstead.com",
    "fromName": "Simpkins, Michelle",
    "subject": "First Amendment to Contract - For Execution",
    "date": "Wed 06/10/2021",
    "time": "10:24",
    "junkScore": "SUSPICION SCORE",
    "nudgeTxt": "PLACEHOLDER",
    "toEml": "alex.carter@anneon.com",
    "gtLabel": "e",
    "folder": "inbox",
    "bodyURL": "/l6.html",
    "CCeml": "",
    "height": 316,
    "previewTxt": "Alex, Enclosed please find the First Amendment to Contract for your review an..."
  },
  {
    "id": 24,
    "fromEml": "ravi.thuraisingham@anneon.com",
    "fromName": "Thuraisingham, Ravi",
    "subject": "RE: Neural Networks",
    "date": "Wed 06/10/2021",
    "time": "09:29",
    "junkScore": "SUSPICION SCORE",
    "nudgeTxt": "PLACEHOLDER",
    "toEml": "alex.carter@anneon.com",
    "gtLabel": "l",
    "folder": "inbox",
    "bodyURL": "/l16.html",
    "CCeml": "",
    "height": 1044,
    "previewTxt": "Alex, here is a power point slide that provides a draft outline of the problem at ..."
  },
  {
    "id": 30,
    "fromEml": "kislince@er.oge.com",
    "fromName": "Kissing, Cynthia E",
    "subject": "FW: Anneon Deal from 17-Oct-17",
    "date": "Tue 05/10/2021",
    "time": "16:13",
    "junkScore": "SUSPICION SCORE",
    "nudgeTxt": "PLACEHOLDER",
    "toEml": "alex.carter@anneon.com",
    "gtLabel": "e",
    "folder": "inbox",
    "bodyURL": "/l22.html",
    "CCeml": "schurman.ii@anneon.com, schurmgr@er.oge.com, burrows@anneon.com",
    "height": 918,
    "previewTxt": "Alex, Will you advise if you have completed the transactions per our discussio..."
  },
  {
    "id": 8,
    "fromEml": "zoom@anneon.formidable.it",
    "fromName": "anneon.com ZoomCall",
    "subject": "ZOOM Conference Call - October 04, 2021 @ 8:30 - 9:15am",
    "date": "Tue 05/10/2021",
    "time": "15:23",
    "junkScore": "SUSPICION SCORE",
    "nudgeTxt": "PLACEHOLDER",
    "toEml": "alex.carter@anneon.com",
    "gtLabel": "p",
    "folder": "inbox",
    "bodyURL": "/p8.html",
    "CCeml": "",
    "height": 245,
    "previewTxt": "Hi Alex, You missed a scheduled Zoom conference meeting from 020-2085-5..."
  },
  {
    "id": 13,
    "fromEml": "hunter.williams@grandecom.com",
    "fromName": "Hunter Williams",
    "subject": "FW: Service Agreement",
    "date": "Tue 05/10/2021",
    "time": "14:44",
    "junkScore": "SUSPICION SCORE",
    "nudgeTxt": "PLACEHOLDER",
    "toEml": "phillip.allen@anneon.com, alex.carter@anneon.com",
    "gtLabel": "e",
    "folder": "inbox",
    "bodyURL": "/l5.html",
    "CCeml": "",
    "height": 558,
    "previewTxt": "Alex/Phillip, I will need Two (2) signed copies of the agreement. Hunter Willia..."
  },
  {
    "id": 33,
    "fromEml": "dmcelduff@nymex.com",
    "fromName": "McElduff, Daniel",
    "subject": "RE:",
    "date": "Tue 05/10/2021",
    "time": "12:17",
    "junkScore": "SUSPICION SCORE",
    "nudgeTxt": "PLACEHOLDER",
    "toEml": "alex.carter@anneon.com",
    "gtLabel": "e",
    "folder": "inbox",
    "bodyURL": "/l25.html",
    "CCeml": "",
    "height": 612,
    "previewTxt": "Alex, Bo Collins would like to speak with you.  Can you forward me your phone..."
  },
  {
    "id": 42,
    "fromEml": "r.shepperd@anneon.com",
    "fromName": "Shepperd, Tammy R.",
    "subject": "Security access",
    "date": "Tue 05/10/2021",
    "time": "11:32",
    "junkScore": "SUSPICION SCORE",
    "nudgeTxt": "PLACEHOLDER",
    "toEml": "steve.woods@anneon.com, susan.lopez@anneon.com, janelle.duree@anneon.com",
    "gtLabel": "o",
    "folder": "inbox",
    "bodyURL": "/l34.html",
    "CCeml": "alex.carter@anneon.com",
    "height": 194,
    "previewTxt": "Attached is the list of employees who should be allowed access to ECS on Sun..."
  },
  {
    "id": 15,
    "fromEml": "greg.whalley@anneon.com",
    "fromName": "Whalley, Greg ",
    "subject": "RE: * Confidential * Sep distribution",
    "date": "Tue 05/10/2021",
    "time": "10:07",
    "junkScore": "SUSPICION SCORE",
    "nudgeTxt": "PLACEHOLDER",
    "toEml": "alex.carter@anneon.com",
    "gtLabel": "o",
    "folder": "inbox",
    "bodyURL": "/l7.html",
    "CCeml": "",
    "height": 1098,
    "previewTxt": "Wow!  this looks complicated.  let me get some help on this and get back to you..."
  },
  {
    "id": 1,
    "fromEml": "sam.jones@annéon.com",
    "fromName": "Sam Jones",
    "subject": "URGENT",
    "date": "Tue 05/10/2021",
    "time": "10:04",
    "junkScore": "SUSPICION SCORE",
    "nudgeTxt": "PLACEHOLDER",
    "toEml": "alex.carter@anneon.com",
    "gtLabel": "p",
    "folder": "inbox",
    "bodyURL": "/p1.html",
    "CCeml": "",
    "height": 270,
    "previewTxt": "Hi Alex, I know you're working from home, but I really hope you're online right n..."
  },
  {
    "id": 39,
    "fromEml": "caroline.abramo@anneon.com",
    "fromName": "Abramo, Caroline",
    "subject": "S+P Commodity Index",
    "date": "Tue 05/10/2021",
    "time": "10:01",
    "junkScore": "SUSPICION SCORE",
    "nudgeTxt": "PLACEHOLDER",
    "toEml": "alex.carter@anneon.com",
    "gtLabel": "l",
    "folder": "inbox",
    "bodyURL": "/l31.html",
    "CCeml": "",
    "height": 1058,
    "previewTxt": "hi- not sure if you saw this with all the crap going on lately or have seen these ..."
  },
  {
    "id": 43,
    "fromEml": "tanya.rohauer@anneon.com",
    "fromName": "Rohauer, Tanya ",
    "subject": "AIG positions",
    "date": "Tue 05/10/2021",
    "time": "08:57",
    "junkScore": "SUSPICION SCORE",
    "nudgeTxt": "PLACEHOLDER",
    "toEml": "alex.carter@anneon.com",
    "gtLabel": "l",
    "folder": "inbox",
    "bodyURL": "/l35.html",
    "CCeml": "joey.taylor@anneon.com",
    "height": 226,
    "previewTxt": "Alex, As discussed, the AIG exposure is $57MM, and it is distributed among th..."
  }
]
